Torrscrape/__init__.py
Torrscrape/main.py
Torrscrape-1.1.5.dist-info/LICENSE
Torrscrape-1.1.5.dist-info/METADATA
Torrscrape-1.1.5.dist-info/WHEEL
Torrscrape-1.1.5.dist-info/entry_points.txt
Torrscrape-1.1.5.dist-info/top_level.txt
Torrscrape-1.1.5.dist-info/RECORD
