Metadata-Version: 2.1
Name: Torrscrape
Version: 1.1.5
Summary: Torrscraper is a command line tool to search and download torrents from the command line.
Author: Tanish
Author-email: sharmatanish097654@gmail.com
Keywords: python,torr,torrent,torrscrape,jackett,Torrscrape
License-File: LICENSE
Requires-Dist: requests
Requires-Dist: qbittorrent-api
Requires-Dist: pandas
Requires-Dist: click
Requires-Dist: rich
